{
  "id": 1117,
  "jad_id": "jad_occurrence__1117",
  "work": [
    {
      "title": "Glossa Ordinaria",
      "author": "Glossa Ordinaria"
    }
  ],
  "position_in_work": "Dan. 11",
  "text_paragraph": "FILII QUOQUE PREVARICATORUM. Pugnantibus contra se Magno Antiocho et ducibus Ptolomei, Iudea in medio posita in contraria studia scindebatur, aliis Antiocho, aliis Ptolomeo consentientibus vel faventibus. Denique Onias sacerdos Domini assumptis plurimis Iudeorum fugit in Egyptum, et a Ptolomeo honorifice susceptus, accepit regionem que Heliopoleos vocabatur, et - concedente rege - templum extruxit in Egypto simile Iudeorum, templo quod permansit usque ad imperium Vespasiani annis ducentis quinquaginta Ipsa autem urbs que vocabatur Onie, dimicantibus postea adversum Romanos Iudeis, usque ad solum deleta est, ut neque urbis neque templi ullum restaret vestigium. Sub occasione igitur Onie pontificis, infinita Iudeorum agmina in Egyptum confugerunt. Eo tempore, et Cyrene eorum multitudine repleta est. Asserebat enim se Onias Isaiek implere vaticinium scribentis: «Erit altare Domini in Egypto et titulus eius in terminis eius et hoc est: Filii prevaricatorum populi» etc."
}