{
  "id": 1061,
  "jad_id": "jad_occurrence__1061",
  "work": [
    {
      "title": "Postillae in Bibliam",
      "author": "Hugh of Saint-Cher"
    }
  ],
  "position_in_work": "Cant. 8",
  "text_paragraph": "Ibi corrupta est mater tua] id est Synagoga, que tam Ecclesie Gentium, quam ipsius Synagoge pro fine temporum mater est. Corrupta e st c orruptione, scilicet triplici. Mortis, ut non regeneraretur ad vitam. Thori, ut vero sponso relicto, spiritualem Barabbam id est Diabolum adulterum peteret sibi dari. Unde Ier. 2.d. Sub omni ligno frondoso prosternaberis meretrix. Quod de ligno Crucis potest exponi, de quo cantamus. <versus> Nulla silva talem profert. Fronde, flore, germine. Os. 2.d. Iudicate matrem vestram etc. Tertia est corruptio, scilicet invidie, de qua Prv. 14.d. Putredo ossium invidia. \n {c} Ibi violata est genitrix tua] lex, scilicet vel ipsa Synagoga, exteriori violatione per Titum et Vespasianum facta. Vel sicut quidam libri apocryphii dicunt quod lignum vetitum fuit ista malus, super qua arbore corrupta est mater totius Ecclesie, scilicet humana natura et violata genitrix, scilicet Eva. Ut sit sensus. Sub arbore Crucis vitam suscepit Ecclesia et sub eadem arbore, ut sit simplex relatio id est sub arbore ligni vetiti corrupta est mater eius et violata genitrix, scilicet tam Eva, quam humana natura. Arboris huius vel ligni vivificantis, scilicet Crucis quadruplex est dimensio, longitudo, latitudo, sublimitas et profundum. Longitudo est ipsius Crucis usque in finem seculi predicatio. Latitudo vero eiusdem, predicatio usque ad terminos orbis terrarum. Sublimitas gratia celestis virtute Crucis desuper infusa credentibus. Profundum vero ipsum Crucis mysterium, sive arcanum, quo deceptus fuit hostis antiquus. Sub hoc signo suscitatum est genus humanum quod sub eodem in specie, vel genere corruptionem mortis in muliere susceperat, quando ad lignum vetitum extenderat manum. Unde cantat Ecclesia : « Ipse lignum tunc notavit, Damna ligni, ut solveret ». Vel arbor ista potest dici penitentia, seu bona vita, sub qua qui eam corde non ficto amplectitur, a Domino suscitatur. Cuius longitudo est perseverantia usque in finem. Iuxta illud. Qui perseveraverit usque in finem etc. Mt. 10.c. Unde et Dominus donec fuit mortuus, non fuit de Cruce depositus. Latitudo recogitatio circumquaque omnium peccatorum. Iuxta illud Is. 38.c. Recogitabo tibi omnes annos etc. Sublimitas est spes glorie, Profunditas vero spes venie vel misericordie. Fructus huius arboris mali, sunt exercitia pietatis. Radix vero electio predestinationis, a qua tam vita arboris, quam succus et folia et fructus et robur originem habent, vel trahunt. Vita huius arboris est fides. Hab. 2.a. Iustus ex fide vivit. Succus, devotio. Folia, verba, sive oratio. Fructus, operatio. Robur, tolerantia. Sub hac tamen arbore corrumpuntur hypocrite et violantur, qui bonam vitam eligunt, non recta intentione, qui in Canonica Iude, dicuntur arbores autumnales bis mortue. Que igitur te ita suscitavi, te tantum {3. 137rb} exaltavi."
}