{
  "id": 787,
  "jad_id": "jad_occurrence__787",
  "work": [
    {
      "title": "Commentary Isaiah",
      "author": "Haimo of Auxerre"
    }
  ],
  "position_in_work": "B3, Ch43",
  "text_paragraph": "Sequitur: Et conversus est eis in inimicum, et ipse debellavit, illis recedentibus de viis ejus, et contra voluntatem ejus incedentibus, conversus est eis in inimicum de misericorde in immisericordem, et debellavit eos saepe p. 1057C | per hostes eorum, sicut in libro Judicum, aliisque historiis et libris propheticis abundantissime declaratur. Potest autem et hoc ad tempus incarnationis ejus referri, quando illis nolentibus credere in se conversus est eis in hostem, qui eorum infirmos sanaverat, mortuosque suscitaverat, et debellavit eos per Romanos quadragesimo secundo anno ascensionis suae. \n \n ¶ \n « Et recordatus est dierum saeculi Mosi populi sui. » Deus omnipotens qui de protectore mutatus in adversarium populo Judaeorum, qui irritaverunt eum, et ad iracundiam provocaverunt: postquam debellavit eos per Romanos, recordatus est dierum saeculi, id est, recordatus dierum antiqui temporis, quando eduxit eos de Aegypto. Et recordatus est p. 1057D | Mosi servi sui qui interpellavit pro eis in deserto dicens: « Aut dimitte eis hanc noxam, aut dele me de libro tuo *. » Recordatus est etiam populi sui qui salvatus oratione Mosi, dum eum vellet percutere usque ad internecionem. Idcirco autem horum recordatus est, quia non erat qui levaret pro eis orationem et a peccato infidelitatis eos liberaret, sicut quondam Mosi oratione et obtentu liberati sunt a flagello et ab errore idololatriae."
}