{
  "id": 1621,
  "jad_id": "jad_occurrence__1621",
  "work": [
    {
      "title": "Postillae in Bibliam",
      "author": "Hugh of Saint-Cher"
    }
  ],
  "position_in_work": "Rev. 16",
  "text_paragraph": "Dicit ergo et abiit primus Angelus, pe r quem significatur primus ordo predicatorum, id est apostolorum, qui contra Iudeos predicaverunt et effudit phialam suam in terra , id est iracundiam Dei terrenis Iudeis imminentem nuntiavit et factum est vulnus sevum ac pessimum in homines , id est in Iudeos et habebant characterem bestie, qu i erant Antichristo conformes, in sanctorum persecutione: et ideo miseri Iudei carum eum habebant, quia Diabolus, qui docebat Antichristum, illos informabat et eos, qui adorabant bestiam et imaginem eius. Im ago eius fuit Simon magus, Arianus, Sabellius, Nero, Constantinus, Photinus, Iulianus etc. huiusmodi, quos Iudei et alii sui temporis adoraverunt. Imaginem Antichristi, Iudei adhuc venerantur, quia adhuc Messiam futurum prestolantur: tamen cum venerit Antichristus recipient eum, ut magnum prophetam in lege promissum, Dt. 18. Unde dominus dicit Io. 5 : « ego veni in nomine patris mei et non accepistis me; si alius veniet in nomine suo illum accipietis. Il le alius erit Antichristus, ut dicit Glossa; quem plurimi recipient, non solum de Iudeis, sed etiam de Christianis. Unde Sir. 24 : « vidi cunctos iuvenes, qui ambulant sub sole, cum adolescente, se cundum Glossam, id est Antichristo, qui consurget pro eo, id est pro Christo: infinitus numerus est populi omnium qui fuerunt ante eum: et qui postea futuri sunt, non letabuntur in eo. In his sevum factum est vulnus, qu ia dispersi sunt per Romanos et venditi pro uno denario triginta, sub Valeriano et pessimum, qu od numquam sanabitur, quia sunt a domino abiecti et reprobati. De quo dicit dominus, Io. 15 : « si non venissem et locutus eis non fuissem etc. Sed numquid Christus eos vulneravit? Absit. Sed Christo predicante per se et per apostolos et ipsis nolentibus audire, Diabolus vulneravit eos et excecavit. Et secundus. Se cunda pars est de secundo Angelo et secunda plaga. Est autem secundus Angelus secundus ordo predicatorum, qui scilicet post expulsionem apostolorum de Iudea gentibus predicaverunt. Mare, di citur gentilitas, propter fervorem impietatis, que regnavit tunc in eis, quando fuit secunda persecutio Ecclesie, sicut supradictum est octavo capitulo, ibi, secundus Angelus tuba cecinit et tamquam mons magnus ardens missus est in mare. Tu nc facta est phiala secunda, id est secundi Angeli effusio, id est divine ultionis comminatio. Sed cum supra iam sufficienter actum sit de his septem Angelis, per quos significantur septem ordines predicatorum, qui in septem statibus Ecclesie et septem persecutionibus eius predicaverunt et consolati sunt eam, quare hic iterum repetitur de illis? Ad hoc solum, nostra Glossa dicit, quod supra actum est de Angelis, inquantum consolabantur Ecclesiam in tribulationibus, que ei inferebantur a malis: hic autem agitur de eisdem inquantum comminantur penam inferendam malis, quod iterum facit ad consolationem beatorum: et si ibi supra erat aliquod verbum de damnatione malorum, hoc ponebatur incidenter ad consolationem sanctorum. Ibi ergo agitur de penis illatis sanctis a malis, hic autem de penis inferendis malis a sanctis. Dicit ergo et secundus Angelus effudit phialam suam , id est secundus ordo predicantium, id est discipuli expulsi a Iudeis divinam ultionem venturam super gentiles nuntiaverunt. Et factus est sanguis tamquam mortui , id est illa ultio divina, quam illi nuntiabant, erit irrevocabilis, sicut non est regressus a morte in vitam. Unde Iob. 15 : « non credit frustra errore deceptus, quod aliquo pretio redimendus sit. Omnis anima vivens, mortua est in mari , id est omnes illi qui consentiebant tyrannis persequentibus discipulos, qui videbantur vivere, eo quod non persequebantur per se discipulos, damnabuntur cum illis qui per seipsos persequebantur, quia consentiunt."
}