{
  "id": 2019,
  "jad_id": "jad_occurrence__2019",
  "work": [
    {
      "title": "Commentary Isaiah (I)",
      "author": "Hrabanus Maurus"
    }
  ],
  "position_in_work": "B1",
  "text_paragraph": "Sicut in bona parte pro varietate virtutum montes appelantur et colles, sic item impios pro diversitate viciorum et maxime superbie, alii montes sunt alli colles, super quos erit dies domini, de quibus in Ezechiel scriptum est, hec dicit adonai dominus, montibus et collibus, ecce inducam super vos gladium, et dissipabuntur excelsa vestra, et conterentur are vestre, et reliqua, et super omnem turrem excelsam, et super omnem murum munitum, qui ad vespasiani et adrianique hec referunt tempora, corporaliter dicunt impleta que scripta sunt, quod non turris excelsa non firmissimus murus, non ulla navium multitudo et negotiationis industria, adversum vim romani exercitus potuerit prevalere, sed in tantam habitatores iudee venisse formidinem, ut et ipsi cum coniugibus ac liberis, auro et argento que sibi auxilio fore estimabant, in foveas terre dimersi sunt, et pro fundissima antra sectari, si enim voracium et lux uriosorum veter est deus, quare non avari aurum et argentum appelletur deus, alii hec ad babilonia refereunt tempora"
}