{
  "id": 397,
  "jad_id": "jad_occurrence__397",
  "work": [
    {
      "title": "Commentaria in Ezechielem",
      "author": "Hieronymus Sophronius Eusebius"
    }
  ],
  "position_in_work": "B2",
  "text_paragraph": "Cum, inquit, propter superiores causas abominationum populi avertero faciem meam ab eis, et nequaquam eos dignos meis oculis judicavero: tunc violabunt arcanum meum, quod significat Sancta sanctorum, pro quo Septuaginta, visitationem transtulerunt (ut in sanctis Dei fuisse praesentiam demonstrarent) et irrumpent p. 0073B | in ea impii et pestilentes terrae: quae exceptis sacerdotibus soloque pontifice nullus alius audebat intrare. Quod scimus et a Babyloniis, et a rege Antiocho Cneoque Pompeio, et ad extremum factum esse sub Vespasiano et Tito, quando templum captum atque subversum est, et omnia perpetrata quae sequens prophetae sermo complectitur. Ad nostra quoque mala opera avertit Deus faciem suam: et quia aversa est facies, ideo Dei violatur arcanum, ut pro sacerdotibus et sanctis Dei pestilentes ingrediantur, et universa contaminent: ut qui locus esse debuit sanctitatis, fiat locus immunditiae, juxta illud Evangelicum: Domus Patris mei domus orationis vocabitur: vos autem fecistis illam speluncam latronum"
}