{
  "id": 328,
  "jad_id": "jad_occurrence__328",
  "work": [
    {
      "title": "Commentaria in duodecim prophetas minores",
      "author": "Rupert of Deutz"
    }
  ],
  "position_in_work": "Zach., B4",
  "text_paragraph": "Usque ad praesentem diem, ait B. Hieronymus, perfidi coloni p. 0784B | post interfectionem servorum, et ad exercitum Filii Dei, excepto planctu, prohibentur ingredi Hierusalem, et ut ruinam eis liceat suae flere civitatis, pretio redimunt, ut qui quondam emerant sanguinem Christi, emant lacrymas suas, et ne fletus quidem eis gratuitus sit. Videas in die quo capta est a Romanis, et diruta Hierusalem, venire populum lugubrem, confluere decrepitas mulierculas et senes pannis annisque obsitos, in corporibus et in habitu suo iram Domini demonstrantes. Profecto qui superius dixerat illis qui jejunaverant et planxerant per septuaginta annos, propter exterminium quod fecerant Babylonii: Nunquid jejunium jejunasti mihi?"
}