{
  "id": 796,
  "jad_id": "jad_occurrence__796",
  "work": [
    {
      "title": "Historia Scholastica",
      "author": "Petrus Comestor"
    }
  ],
  "position_in_work": "Dan., Ch10",
  "text_paragraph": "Quod vero sequitur: « Et civitatem et sanctuarium dissipabit populus, » ad septuaginta hebdomades non pertinet. Sed prophetato tempore adventus Christi et mortis, prophetavit quid venturum erat populo, qui noluit eum recipere, dicens: « Et dissipabit civitatem et sanctuarium, » populus scilicet Romanus, « cum duce suo venturo, et finis ejus erit vastitas, et post finem belli statuta » a Deo in aeternum « desolatio. » Et nota quod ex duobus quae hic leguntur, scilicet « ungetur Sanctus sanctorum, » et p. 1460D | « deficiet hostia, » sumitur illud quod solet dici Judaeis: Cum venerit Sanctus sanctorum, cessavit unctio vestra. Africanus huic enumerationi Bedae consonat in principio, sed in fine differt. Non enim extendit septuaginta hebdomades, nisi usque ad decimum quintum annum Tiberii, in quo baptizatus est Christus. Tertullianus vero inchoat numerare hebdomadas illas a primo anno Darii, in quo egressus est sermo a Domino ad Danielem per angelum, ut iterum reaedificarentur muri Jerusalem. Et extendit eas usque ad captivitatem factam per Romanos. Et tunc pertinet ad septuaginta hebdomades; quod dictum est, quia « civitatem, et sanctuarium dissipavit populus cum duce venturo. » Hebraei sic exponunt: « Septuaginta hebdomades abbreviatae sunt p. 1461A | super populum tuum. » Quasi dicat: O Daniel, scito ab hac die, qua nunc tibi loquor. Erat autem annus primus Darii, qui occidit Baltassar, et regnum Chaldaeorum in Persas Medosque transtulit, usque ad septuagesimum annum hebdomadarum, id est usque ad annos quadringentos nonaginta. Haec populo tuo per partes accident: primum propitiabitur tibi Deus sicut precaris, et delebitur peccatum, et finem accipiet praevaricatio. Nunc enim, urbe et templo destructis, in luctu est populus, sed in brevi restaurabitur, et non solum in his septuaginta hebdomadibus haec fient, sed nascetur Christus justitia sempiterna, et signabitur visio, et prophetes, ut propheta non inveniatur in Israel, et ungatur Sanctus sanctorum, de quo dicitur in Psalmo: « Propterea p. 1461B | unxit te Deus tuus oleo laetitiae prae consortibus tuis *, qui dicit: « Sancti estote, quoniam et ego sanctus sum"
}