{
  "id": 42,
  "jad_id": "jad_occurrence__42",
  "work": [
    {
      "title": "Sermones",
      "author": "Aelred of Rievaulx"
    }
  ],
  "position_in_work": "Sermo 21",
  "text_paragraph": "Ne laeteris, Philisthaea omnis tu; quoniam comminuta est virga percussoris tui. Recordamini, fratres, consilium illud, quod contra Dominum populus ille legitur collegisse: in quo a Caipha pontifice decretum est unum mori hominem, ne gens tota percat. Si enim, inquiunt, dimittimus eum sic, omnes credent in eum; et venient Romani, et tollent nostrum locum et gentem (Joan. XI). Trepidaverunt timore, ubi non erat timor (Psal. XIII). Viderat in somnis sanctus patriarcha Joseph, quod esset a fratribus adorandus. Quod ne fieret, venditur in Aegyptum (Gen. XXXVII); per quod tamen accidit, ut fieret."
}