{
  "id": 1935,
  "jad_id": "jad_occurrence__1935",
  "work": [
    {
      "title": "Dialogus libri uitae",
      "author": "Rodericus Ximenius de Rada archbishop Toledo"
    }
  ],
  "position_in_work": "B3, Ch4",
  "text_paragraph": "Quod dicit: Donec auferatur luna, nosti luna crescit | neccesario et decrescit; unde per eam uetus intelligitur testamentum, quod + aliquando incrementum etiam non + Iudeorum rebellio discidium procurauit; uictrix Roma populum et legalia stirpauit, et tunc pax tenporis domini Ihesu Christi cepit post pasionem anno XL-o perturbari, cum incipit Titus prelium contra tuos et ideo luna figura ueteris testamenti dicitur auferenda; nunquam enim luna a celli auferetur cum sit perpetua creatura. \n De hoc Zacharias: Lauda et letare, filia Sion, quia ecce ego filius habitabo in medio tui factus homo, ait dominus; et aplicabuntur gen<te>s multe ad dominum in die illa et erunt mihi in populum, et ideo habitabo in medio tui, et scies quia dominus pater me, o ecclesia, ad te missit; ideo literam sic destinxi, quia hic metaplasmum ingerit mutacio personarum, et cum dicit: Dominus missit me ad te, mitens pater, missus filius, cum mititur, ecclesia designatur."
}