{
  "id": 961,
  "jad_id": "jad_occurrence__961",
  "work": [
    {
      "title": "Commentary Psalms",
      "author": "Remigius of Auxerre"
    }
  ],
  "position_in_work": "Ps.30",
  "text_paragraph": "Merita eorum deducant eos ex adverso, ut cum servi tui sint ad dexteram, illi dedantur ad sinistram: hi in vitam aeternam, illi in supplicium aeternum *, vel deducantur hic in infernum, id est, in consummatam nequitiam. Et tandem muta fiant labia dolosa, labia inimicorum Christi et Ecclesiae, qui cum viderint illos quos habuerunt in derisum *, in gloria, se autem in miseria, non ultra poterunt contradicere veritati. Ostendit quae sint illa labia dolosa, scilicet quae hic loquuntur adversus justum iniquitatem. Judaei adversus Christum, Non habemus regem nisi Caesarem * . Et increduli p. 0296A | et haeretici adversus fidelem populum, isti pacem annuntiant, illi bellum inferunt: isti salutem, illi mortem: isti amicitiam, illi odium. In superbia, sequendo quae Christus contemnenda monstravit. Et in abusione, id est, contemptu, quia amatores mundi contemptores sunt fidei. Et Judaei in Christum superbe locuti sunt: Nolumus hunc regnare super nos * . Et in abusione, Ne forte veniant Romani, et tollant nostrum locum et gentem * . Quasi dicat: Ideo loquitur adversus justum iniquitatem, quia non attendunt quam dulcis est Dominus."
}