{
  "id": 82,
  "jad_id": "jad_occurrence__82",
  "work": [
    {
      "title": "Commentary Psalms",
      "author": "Peter Lombard"
    }
  ],
  "position_in_work": "Ch41",
  "text_paragraph": "Quemadmodum, etc. Titulus In finem intellectus, vel intellectu filiis Core. Core, sicut supra diximus, calvaria interpretatur, qui fuit locus Dominicae p. 0414D | passionis quae in Calvaria facta est. Filii ergo Core, sunt filii calvi, id est Christi in calvo Eliseo praesignati. Dum Eliseus ascenderet de Jericho in Bethel egressi sunt de Bethel XLII pueri, irridentes Eliseum, et dicentes: Ascende, calve, ascende, p. 0415A | calve! Tunc jussit Eliseus duos ursos exire de saltu, a quibus pueri interfecti sunt (IV Reg. II): ita et Christus, cum ascenderet in Bethel, id est cum carne assumpta veniret ad Synagogam, quae prius erat domus Dei, quod sonat Bethel, irrisus est a parvulis: Ascende, calve, clamantibus, id est Judaeis puerili fatuitate clamantibus: Tolle, tolle, crucifige eum! (Joan. XIX.) qui devorantur a duobus ursis, id est a diabolo et angelis ejus, vel a Tito et Vespasiano, quos Deus ad destructionem Judaeorum misit XLII anno post Christi resurrectionem, sicut illi pueri quadraginta duo fuerunt a duabus bestiis devorati."
}