{
  "id": 61,
  "jad_id": "jad_occurrence__61",
  "work": [
    {
      "title": "Speculum Ecclesiae",
      "author": "Honorius Augustodunensis"
    }
  ],
  "position_in_work": "X Sunday",
  "text_paragraph": "In hac itaque obsidione legitur quo undecies centena milia fame perierint totidemque gladio perempti sint, ejusdem numeri in captivitatem distracti, trecenti in ultionem Dominicae necis crucifixi sunt. Traditur etiam quod XXX pro denario venditi sunt, sicut ipsi Dominum pro XXX denariis tradiderunt. Sic, karissimi, reddidit Dominus septuplum in sinu eorum qui p. 1052B | effuderunt sanguinem sanctorum (Psal. LXXVIII). Sic relicta est domus deserta (Luc. XIII) quam ipsi speluncam latronum fecerunt (Matth. XXI); sicque Romani et locum et gentem illorum tulerunt (Joan. XI). En, dilectissimi, audistis captivitatem Judaeorum; cavendum est nobis a captivitate daemoniorum. Illa enim scripta est ad correctionem nostri, ne nos incautos circumcludant castra hostis maligni. Etenim ut nos essemus captivitate liberi, summi Regis Filius datus est obses pro redemptione nostri. Atque ut hoc tenaciter nostrae memoriae imprimatur, panis Christi in modum denarii formatur: quia profecto ille pro XXX denariis traditus est in manu impiorum qui verus denarius dabitur in vinea usque ad vesperam laborantibus praemium omnium justorum."
}