{
  "id": 837,
  "jad_id": "jad_occurrence__837",
  "work": [
    {
      "title": "Enarratio in Baruch prophetam",
      "author": "Dionysius Cartusianus"
    }
  ],
  "position_in_work": "Ch1",
  "text_paragraph": "am et AEgyptios ac Judaeos in AEgypto manentes, prophetavit Jeremias a rege Babylonis vastandos, ut in Jeremia legitur. \n \n 2. In anno quinto a combustione Jerusalem, facta per Nabuzardan principem militiae Nabuchodonosor regis, in septima die mensis, forsitan primi, anni illius quinti, quoniam nomen mensis non exprimitur hic; in tempore quo ceperunt Chaldaei Jerusalem. \n \n Hoc additur, ad innuendum quod Judaei tunc computabant annos a tempore Babylonicae captivitatis, sicut jam numerant annos a tempore captivitatis et destructionis plebis ac urbis suae Jerusalem per Romanos sub Tito. \n \n Sic que quod ait, In tempore, potest exponi, A tempore. \n \n 3. Et legit Baruch verba libri hujus ad aures Jechoniae filii Joakim regis Juda, et ad aures universi populi Judaici venientis ad librum. \n \n Baruch namque propter sapientiam suam et propter familiaritatem suam cum Jeremia habitam, fuit famosus: idcirco venerunt ad eum. \n \n 4. Et ad aures potentium filiorum regum Juda, id est eorum qui nati fuerunt de semine regum Juda, quorum aliqui fuerunt in Babylone, prout in Daniele habetur: quorum unus fuit Daniel, quem Josephus et Epiphanius dicunt fuisse de regio semine. \n \n Septuaginta tamen interpretes insinuant eum fuisse de stirpe Levi: quod poterit concordari, quoniam illae duae tribus fuerunt frequenter matrimonialiter junctae. \n \n Hinc in Isaia Dominus dixit ad Ezechiam: De filiis tuis erunt eunuchi in palatio regis Babylonis."
}