{
  "id": 1124,
  "jad_id": "jad_occurrence__1124",
  "work": [
    {
      "title": "Glossa Ordinaria",
      "author": "Glossa Ordinaria"
    }
  ],
  "position_in_work": "Mt. 26",
  "text_paragraph": "An putas \n marg.| AN PUTAS. Quasi diceret: non indigeo auxilio apostolorum duodecim qui possum habere duodecim legiones angelorum, in quibus sunt septuaginta duo millia, quibus omnium gentium lingua exprimitur. Innuit autem non esse verendum si contra Iesum omnes nationes insurgant, cum multo fortiores ipse habeat exercitus angelorum Aliter. Hic numerus significat omne genus hominum cum romano imperio contra Iudeos certaturum, hi sunt angeli Dei qui post resurrectionem anno quadragesimo secundo, cum Tito et Vespasiano perdiderunt homicidas illos, et civitatem illorum succenderunt. \n quia non possum rogare Patrem meum et exhibebit mihi modo plusquam duodecim legiones angelorum? \n Mt. 26:54 \n Quomodo ergo implebuntur Scripture quia sic oportet fieri? \n interl.| quibus dictum est: «Tamquam ovis ad occisionem ductus est»z etc. \n z Is. 53, 7: « Oblatus est quia ipse voluit, et non aperuit os suum ; sicut ovis ad occisionem ducetur, et quasi agnus coram tondente se obmutescet, et non aperiet os suum » ; cf. etiam Act. 8, 32."
}