{
  "id": 2120,
  "jad_id": "jad_occurrence__2120",
  "work": [
    {
      "title": "Liber de temporibus et aetatibus et cronica imperatorum",
      "author": "Albertus Milioli"
    }
  ],
  "position_in_work": "Ch9",
  "text_paragraph": "VIIII. De Galba et Ottone et Vitello et Vespasiano et aliis gestis. \n Anno ab incarnatione Domini LXXII. post mortem Neronis Galba in Yberniar, Otto Rome, \n Vitellus in Germania, Vespasianus in Palestina electi sunt ad imperium. Nero namque contra Iudeos \n Vespasianum $ miserat; sed Galba VII° mense *capite truncatur, Otto levi prelio victus se ipsum \n occidit. Vitellus a ducibus Vespasiani occiditur. Huiust temporibus fuit Linus papa. \n Itaque Vespasianus, exercitum filio Tito conmendans, Romam venit et confirmatus regnavit\" \n an. VIIII, men. XI, di. XXII. Qui moderatissime rexit imperium. Erat enim iustus, largus, letusy, \n paciens, inmemor offensarum. Ecclesia que Ierosolimis congregata fuerat, responso accepto, transivit ad \n castrum Pellam nomine trans Iordanem. Ablatis iustis viris Titus anno secundo imperii patris \n Iudeam et Ierusalem diebus açimorum subvertit, diebus merito, quibus Dominum occiderunt, alii \n occiduntur gladio, alii fame, usque adeo, quod matres filios comederantw. Alii vero igne conbusti sunt, \n alii venumdati, alii captivati, usque ad decies centena milia. Hic est igitur ille secundum prophetam \n aper de silva, qui devastavit eam. Fuerunt autem a prima edificatione templi, que fuit sub Salomone, \n \n usque ad hanc ruinam an. III a CII - alii dicunt IIIb LXXXIX; a secunda, que fuit sub Dario, \n DXC; a captivitatee sub Antiquod CCXXXVIII; a passionee Domini XXXIX vel pocius XL, super \n Ysaiam legitur XLII. Hec prodictionemf hec prodigia precesserunt, scilicet cometes, stella \n similis gladio et inmensus fulgor repentinus in templo et voces dicentes: 'Transmigremus hinc', et \n ianua ferreis vectibus munita sponte patefacta, currus et quadrige, armatorum cohortes sacres, et \n vitula in sacrificiis agnam enixa, et prophetia cuiusdam rustici clamantis et nil aliud in ore habentis \n quamh verba hec: 'Vox ab oriente i, vox ab occidentek, vox a quatuor ventis, vox super Ierusalem et \n templum, vox super sponsam et sponsum, ve Israelitis! et divisio civium, quia pars templum, pars \n tenuit arcem, pars reliquam civitatem. Unde Ysaias1: Vox populi de civitate, vox de templo; post ex- \n cidium Iudeorum ex diversis locis convenientes in unum apostoli ceterique discipuli, qui supererant, \n elegerunt Symonem Cleophe filium et Iacobum substitueruntm. Temporibus Vespasiani Achaia, \n Lithia, Rodus, Bizancium, Samos, Trachia et multe alie regiones, quarum quedam libere, quedam sub \n regibus degebant amissibusn regibus, sub Romano imperio rediguntur. Capitolium incenditur, \n quod edificareo incepit."
}