{
  "id": 183,
  "jad_id": "jad_occurrence__183",
  "work": [
    {
      "title": "Commentary Isaiah",
      "author": "Hieronymus Sophronius Eusebius"
    }
  ],
  "position_in_work": "B8, Ch27",
  "text_paragraph": "Et quae quondam fuit speciosa, de qua et in Ezechiele dicitur: Similam, et mel et oleum comedisti, et speciosa facta es vehementer nimis * , et in qua habitat ille de quo scriptum est: Speciosus forma prae filiis hominum * , relinquetur et dimittetur quasi desertum, dicente Domino ad Apostolos: Surgite, abeamus hinc * . Ibi pascetur vitulus, Romanus exercitus, de quo et in alio loco sub nomine apri dictum est: Vastabit eam aper de silva: et singularis ferus depastus est eam * . Et ibi accubabit et consumet summitates p. 0311B | ejus sub metaphora vineae et propaginum ejus, ut nihil in ea viride, nihil remaneat flagellorum, sed omnia consumat inimicus. Juxta LXX, quia non receperunt pastorem bonum: propterea erunt quasi grex derelictus, et patebunt morsibus bestiarum; et nihil in eis viride remanebit, quia siccitas omnia possidebit."
}