{
  "id": 1718,
  "jad_id": "jad_occurrence__1718",
  "work": [
    {
      "title": "Chronographia tripertita",
      "author": "Anastasius Bibliothecarius"
    }
  ],
  "position_in_work": "",
  "text_paragraph": "Interea Maximus, Maximi nepos tyranni, Valentinianum peremit et Eudoxiae vi sociatus imperium quoque optinuit: per quaeque namque quis peccat, per ea quoque et corripitur. \n \n inter haec ergo Eudoxia coartata, nullum fore auxilium a Byzantio Theodosio patre suo et Pulcheria defunctis existimans accersit Gezerichum ad urbem Romam rogans e Maximi tyrannide liberari. \n \n magna vero cum classi Gezerichum Romam navigantem Maximus timens fuga usus est; hi vero, qui cum ipso aderant, interemerunt eum. \n \n praeterea Gezerichus nemine sibi resistente introivit Romam tertia die Maximi fugae et sublatis omnibus pecuniis et civitatis miraculis in naves que receptis, in quibus erant ecclesiastica cimilia tota ex auro lapidibus pretiosis ornata et vasa Hebraica, quae Titus Vespasiani filius post captivitatem Hierosolymarum Romam detulerat, una cum Eudoxia imperatrice ac filiabus eius in Africam navigavit. \n Erat autem Marcianus admodum religiosus et timens deum; qui in letaniis Campi pedes excedebat multa egentibus beneficia praestans. \n quod intuens Anatolius patriarcha et ipse de cetero non phorio portatus secundum morem sed pedes letanias faciens incedebat. \n \n Timotheus autem Helurus molimine usus noctu cellas monachorum circuibat unumquemque vocans ex nomine, quo respondente dicebat: \"ego angelus sum dicere omnibus, ut abscedant a communione Proterii et eorum, qui Chalcedone convenerunt, et Timotheum Helurum in episcopum Alexandriae provehant\"."
}