{
  "id": 685,
  "jad_id": "jad_occurrence__685",
  "work": [
    {
      "title": "De decursu temporum",
      "author": "Haimo of Bamberg"
    }
  ],
  "position_in_work": "B3, Ch2",
  "text_paragraph": "In bis duabus sententiis Eusebii pensandum est, quia vel in Alexandra Ianneo vel filio eius Hircano crisma, id est unctionem, 15 quę. secundum legem fiebat, interisse et finem accepisse dich, cum tamen altius inspicientibus videatur potius finem accepisse unctio regalis in Iechonia et Sedechia, filiis Iosie, qui erant ultimi reges de tribu Iuda, quę sola tribus secundum legem Domini erat regalis. De alia enim tribu qualibet quicumque reges facti sunt, 20 Erstfassung: p. 255 | ut Saul de tribu Beniamin et reges Israhel, de tribu quoque Levi, quę tantum sacerdotalis erat, Aristobolus, Iam/neus, Hircanus, Antigonus, omnes non in beneplacito, sed in ira Dei reges uncti sunt, sicut, si quis de alia tribu quam de tribu Levitica se 5 pontificatui temere ingessit, non Dominum placavit, sed ad iram provocavit, ut Saul et Ozias. Pontificatus quoque post Hircanum fere nonaginta annis quoquo modo duravit, donec Vespasianus Ierusalem funditus evertit. Nam si in Hircano ideo defecisse putetur, quia post eum contra legem administrabatur, cur non 10 potius ante, quando a pluribus, ut a Iasone , Menelao, Lisimacho, Alchimo quoque, pessime usurpatus est, finem accepisse credatur? Quodsi dicet Eusebianus, quia expulsis facinorosis invasoribus rediit sacerdotium legale et ordine suo processit in Leviticis sacerdotibus, congrue poterit ei responderi simili ratione posse 15 astrui apud Iudeos neutrum crisma adhuc prorsus defecisse. Nam apud eos usque hodie permanent plerique de tribu Iuda et de tribu Levi; qui si crismate legali ungantur, cur non officiis suis, scilicet regno et sacerdotio, legaliter fungantur? An quia Ierusalem, metropolis sacerdocii et caput regni eorum, eversa est? Sed Aaron 20 et filii eius in deserto, antequam intrassent in terram promissionis, sacerdotes Domini fuerunt et David, primus rex Iudeorum, antequam Ierusalem in sedem regni edificasset, regnavit in Ebron VII annis."
}