{
  "id": 2382,
  "jad_id": "jad_occurrence__2382",
  "work": [
    {
      "title": "Postilla seu expositio litteralis et moralis super epistolas et evangelia quadragesimalia",
      "author": "Nicolaus de Lyra"
    }
  ],
  "position_in_work": "Joh. 8",
  "text_paragraph": "Et iudicet: Scilicet Deus pater de illis qui me inhonorant, vindictam faciendo de ipsis. Quod factum est, quando in vindicta mortis Christi, destructa est civitas et templum, et populus occisus est et captivatus per Romanos. \n . \n marg.|. 7. Amen, amen dico vobis: Hic probat tertium supra positum, scilicet quod sequens Christum lumen habeat vite : Et dividitur in duas, quia primo ponitur Christi probatio. Secundo Iudeorum obiectio, ibi. Dixerunt ergo. In prima parte dicitur sic : Amen, amen dico vobis. id est fideliter. Et duplicatur ad maiorem affirmationem."
}