{
  "id": 318,
  "jad_id": "jad_occurrence__318",
  "work": [
    {
      "title": "Commentaria in duodecim prophetas minores",
      "author": "Rupert of Deutz"
    }
  ],
  "position_in_work": "Amos, B2",
  "text_paragraph": "Sequitur ergo: « Si erit malum in civitate quod Dominus non fecit? » Et quidem in civitate illa, id est in hoc mundo, « qui in maligno positus est *, » malum esse non potest negari, sed quod Dominus malum ipsum faciat, negare contendunt cives ejusdem civitatis, Deo rebelles et increduli. Exempli gratia: malum venit in civitatem Samariae propter vitulos aureos quos fecit Jeroboam, cujus a peccatis nullus regum Israel recessit, illud videlicet malum quod Israel ab Assyriis captivus ductus est. Malum itidem venit in civitate Jerusalem, ut primum a Babyloniis, et deinde exscinderetur a Romanis. p. 0296B | Nonne hujusmodi malum Dominus fecit? Etenim malum quidem, quod est iniquitas, Dominus non fecit, sed malum, quod est affectio propter iniquitatem, Dominus induxit. Unde hoc comprobari poterit? Ait, « quia non faciet Dominus Deus verbum, nisi revelarit Dominus secretum suum ad servos suos prophetas."
}