{
  "id": 491,
  "jad_id": "jad_occurrence__491",
  "work": [
    {
      "title": "Commentary Hosea",
      "author": "Haimo of Auxerre"
    }
  ],
  "position_in_work": "Ch2",
  "text_paragraph": "Post cujus interfectionem aperta est filiis Israel spes victoriae futurae, pergentesque ceperunt oppidum Hai, interfectis habitatoribus ejus; et moeror eorum in gaudium versus est, ibique spem sumpserunt ubi fuerat desperatio. Sed quia hoc, ut dictum est, factum constat fuisse, videamus quid sibi velint verba p. 0023D | prophetica, qui haec de futuro vaticinatur, dicens: « Et vallem Achor ad aperiendam spem. » Sciendum ergo, quia sicut tunc postquam interfectus est Achar, Judaei sumpserunt spem vincendi hostes, nec ea frustrati sunt; sic nimirum postquam Hierusalem destructa est a Romanis, templumque succensum, et ipsi Judaei interempti et in totum mundum sunt captivati; apostolis caeterisque credentibus aperta est spes victoriae, quia totum mundum fidei Christi subjugaverunt, quodque in umbra praecesserat, id est illud templum et omnium caeremoniarum observationes in spiritualem verterunt intelligentiam, sicut nunc agitur in Ecclesia a fidelibus. Et haec fuit eorum spes victoriae, de qua hic dicitur: « Et vallem p. 0024A | Achor ad aperiendam spem, » subauditur dabo."
}