{
  "id": 209,
  "jad_id": "jad_occurrence__209",
  "work": [
    {
      "title": "Commentary Isaiah",
      "author": "Rupert of Deutz"
    }
  ],
  "position_in_work": "B1, Ch6",
  "text_paragraph": "Iniqui sunt coetus vestri, kalendas vestras, et solemnitates vestras odivit anima mea. Olim nolui, attamen tuli. Nunc autem jam non feram, nam odio profundo odivit haec anima mea. Facta sunt mihi molesta. At ex quo facta sunt mihi molesta, sustinui illa per annos quadraginta. Non statim misi Titum et Vespasianum qui tollerent vestrum et locum et gentem, qui civitatem et templum destruerent, ita ut non remaneret lapis super lapidem, sed sustinui per annos quadraginta. p. 1278A | 481 Laboravi sustinens. Quod tandiu sustinui, labor mihi fuit. Abominabar incensum vestrum, oderam neomeniam et Sabbatum vestrum, oderat anima mea coetus vestros, et stercus solemnitatum vestrarum. Vim quodammodo faciebam animae meae, ut quod oderat sustineret saltem quadraginta annis, et hoc faciens laboravi. Veniant tandem Romani, et hunc laborem demant mihi. Et cum extenderitis manus vestras, subauditur, et foris circumdati armis, et intus fame, et seditionibus afflicti et concisi, avertam oculos meos a vobis. Ne compellar condolere et misereri. Et cum multiplicaveritis orationem, sacrificia certatim offerendo, in templo cruentando, in aspectu hostium, pertinaciam vestram admirantium, non exaudiam. Manus enim vestrae plenae sanguine p. 1278B | sunt. Implestis vobis eas, dicendo: Sanguis ejus super nos et super filios nostros * . Hoc est verbum Domini. Quae porro est lex Dei nostri? Lavamini, mundi estote. Si forte compuncti, aliqui ex vobis dicant ad Petrum, et ad reliquos apostolos meos? Quid faciemus, viri fratres * , ecce dico vobis: Lavamini. Quod est dicere: Poenitentiam agite, et baptizetur unusquisque vestrum in nomine Domini * . Itaque lavamini, mundi estote, id est baptizamini et nolite rursus malis operibus munditiam baptismatis perdere, et ecce audite septem partes adhibendae diligentiae. Auferte malum cogitationum vestrarum ab oculis meis, quiescite agere perverse, discite benefacere. Quaerite judicium, subvenite oppresso, judicate pupillo, defendite viduam."
}