{
  "id": 1976,
  "jad_id": "jad_occurrence__1976",
  "work": [
    {
      "title": "Sermones",
      "author": "John Wyclif"
    }
  ],
  "position_in_work": "Sermo 55",
  "text_paragraph": "Qui nuncios Dei contempserant, tripertiti ut clerici ex avaricia occupati circa cultum templi pro questu habendo, abierunt a Deo in vineam ut sacerdotes et levite. \n \n Templum enim vocatur vinea laici circa temporalia occupati; et hii reges occiderunt prophetas, ut patet Matthei XXIII-o, 37: Jerusalem, Jerusalem que occidis prophetas et lapidas eos qui ad te missi sunt; et sic creverunt in malicia. \n \n Nam filii Israel quibus dedit legem Mosaycam et prophetas tempore regum et sacerdotum, quando regulabantur pessime, renuerunt venire ad fidem incarnacionis, ideo misit exercitum Romanorum cuius duces erant Titus et Vespasianus et occidit homicidas Christi qui erat magni consilii angelus missus ad oves que perierant domus Israel. \n Nam XLII-o anno post ascensionem Domini exercitus Romanorum inclusit Judeos die Pasche in Jerusalem et occidit decies centum millia et succendit Jerusalem igne (ut narrat Josephus De Bello Judaico); et tunc misit Apostolus conversos ad gentes errantes extra viam Domini (ut patet Act. XIII-o) et impleverunt ecclesiam militantem de predestinatis et prescitis. \n Sed ve soli qui non habet caritatem finalis perseverancie, quia omnis talis dampnatur in mortis articulo."
}